tipredict/__init__.py
tipredict/configs.py
tipredict/main.py
tipredict/max.csv
tipredict/max_DAGTransformer.csv
tipredict/max_DAGTransformer_mem.csv
tipredict/max_mem.csv
tipredict/min.csv
tipredict/min_DAGTransformer.csv
tipredict/min_DAGTransformer_mem.csv
tipredict/min_mem.csv
tipredict/preprocess.py
tipredict/models/DAG_Transformer.py
tipredict/models/DAG_Transformer_Encoder_Layer.py
tipredict/models/GAT_torch_geometric.py
tipredict/models/GIN.py
tipredict/models/Graphsage.py
tipredict/models/__init__.py
tipredict/weights/DAGTransformer.pth
tipredict/weights/DAGTransformer_cpu.pth
tipredict/weights/DAGTransformer_mem.pth
tipredict/weights/GAT.pth
tipredict/weights/GAT_cpu.pth
tipredict/weights/GAT_mem.pth
tipredict/weights/GIN.pth
tipredict/weights/GIN_cpu.pth
tipredict/weights/GIN_mem.pth
tipredict/weights/Graphsage.pth
tipredict/weights/Graphsage_cpu.pth
tipredict/weights/Graphsage_mem.pth
tipredict/weights/__init__.py
tipredict-0.2.dist-info/METADATA
tipredict-0.2.dist-info/WHEEL
tipredict-0.2.dist-info/top_level.txt
tipredict-0.2.dist-info/RECORD
