Metadata-Version: 2.1
Name: tipredict
Version: 0.2
Summary: UNKNOWN
Home-page: UNKNOWN
License: UNKNOWN
Platform: UNKNOWN
Requires-Dist: numpy>=1.26.0
Requires-Dist: pandas>=1.3.4
Requires-Dist: tqdm>=4.66.4
